fivesim/__init__.py
fivesim/client.py
fivesim/errors.py
5sim_python-1.0.4.dist-info/LICENCE.txt
5sim_python-1.0.4.dist-info/METADATA
5sim_python-1.0.4.dist-info/WHEEL
5sim_python-1.0.4.dist-info/top_level.txt
5sim_python-1.0.4.dist-info/RECORD
