Metadata-Version: 2.1
Name: 5sim-python
Version: 1.0.4
Summary: A simple Python API for 5sim.net
Home-page: https://github.com/scribesavant/5sim-python
Author: scribesavant
Author-email: scribesavant@gmail.com
License: MIT
Keywords: api 5sim
Classifier: Development Status :: 5 - Production/Stable
Classifier: Intended Audience :: Education
Classifier: Operating System :: Microsoft :: Windows :: Windows 10
Classifier: License :: OSI Approved :: MIT License
Classifier: Programming Language :: Python :: 3
License-File: LICENCE.txt
Requires-Dist: requests
